[
  {
    "image": "../../assets/m1.1.jpg"
  },

  {
    "image": "../../assets/m1.2.jpg"
  },
  {
    "image": "../../assets/m2.1.jpg"
  },

  {
    "image": "../../assets/m2.2.jpg"
  },

  {
    "image": "../../assets/m3.1.jpg"
  },
  {
    "image": "../../assets/m3.2.jpg"
  },
  {
    "image": "../../assets/w1.1.jpg"
  },
  {
    "image": "../../assets/w1.2.jpg"
  },
  {
    "image": "../../assets/w1.3.jpg"
  },
  {
    "image": "../../assets/w2.1.jpg"
  },
  {
    "image": "../../assets/w2.2.jpg"
  },
  {
    "image": "../../assets/w2.3.jpg"
  },
  {
    "image": "../../assets/w3.1.jpg"
  }
]
